twitter_dummyy_bot/action_strategy.py
twitter_dummyy_bot/data_analysis.py
twitter_dummyy_bot/data_collection.py
twitter_dummyy_bot/follow_bot_strategy.py
twitter_dummyy_bot/follow_user_strategy.py
twitter_dummyy_bot/resources.py
twitter_dummyy_bot/sentiment_analysis_strategy.py
twitter_dummyy_bot/setup.py
twitter_dummyy_bot/strategy_interface.py
twitter_dummyy_bot/top_n_strategy.py
twitter_dummyy_bot/trends_data_collection.py
twitter_dummyy_bot/twitter_account.py
twitter_dummyy_bot/twitter_action.py
twitter_dummyy_bot/twitter_api_preparation.py
twitter_dummyy_bot/twitter_bot.py
twitter_dummyy_bot/twitter_data_collection.py
twitter_dummyy_bot/twitter_object_parsing.py
twitter_dummyy_bot-0.0.2.dist-info/LICENSE
twitter_dummyy_bot-0.0.2.dist-info/METADATA
twitter_dummyy_bot-0.0.2.dist-info/WHEEL
twitter_dummyy_bot-0.0.2.dist-info/top_level.txt
twitter_dummyy_bot-0.0.2.dist-info/RECORD
